oos/__init__.py
oos/cli.py
oos/commands/__init__.py
oos/commands/dependence/__init__.py
oos/commands/dependence/cli.py
oos/commands/environment/__init__.py
oos/commands/environment/cli.py
oos/commands/pr/__init__.py
oos/commands/pr/cli.py
oos/commands/spec/__init__.py
oos/commands/spec/cli.py
oos/commands/spec/repo_class.py
oos/commands/spec/spec_class.py
oos/common/__init__.py
oos/common/gitee.py
oos/common/pypi.py
oos/common/utils.py
openstack_sig_tool-1.0.3.data/data/etc/oos/constants.yaml
openstack_sig_tool-1.0.3.data/data/etc/oos/oos.conf
openstack_sig_tool-1.0.3.data/data/etc/oos/openeuler_repo.yaml
openstack_sig_tool-1.0.3.data/data/etc/oos/openeuler_sig_repo.yaml
openstack_sig_tool-1.0.3.data/data/etc/oos/openstack_release.yaml
openstack_sig_tool-1.0.3.data/data/etc/oos/package.spec.j2
openstack_sig_tool-1.0.3.data/data/etc/oos/inventory/all_in_one.yaml
openstack_sig_tool-1.0.3.data/data/etc/oos/inventory/cluster.yaml
openstack_sig_tool-1.0.3.data/data/etc/oos/playbooks/aodh.yaml
openstack_sig_tool-1.0.3.data/data/etc/oos/playbooks/ceilometer.yaml
openstack_sig_tool-1.0.3.data/data/etc/oos/playbooks/cinder.yaml
openstack_sig_tool-1.0.3.data/data/etc/oos/playbooks/cleanup.yaml
openstack_sig_tool-1.0.3.data/data/etc/oos/playbooks/cyborg.yaml
openstack_sig_tool-1.0.3.data/data/etc/oos/playbooks/entry.yaml
openstack_sig_tool-1.0.3.data/data/etc/oos/playbooks/glance.yaml
openstack_sig_tool-1.0.3.data/data/etc/oos/playbooks/gnocchi.yaml
openstack_sig_tool-1.0.3.data/data/etc/oos/playbooks/heat.yaml
openstack_sig_tool-1.0.3.data/data/etc/oos/playbooks/horizon.yaml
openstack_sig_tool-1.0.3.data/data/etc/oos/playbooks/init.yaml
openstack_sig_tool-1.0.3.data/data/etc/oos/playbooks/keystone.yaml
openstack_sig_tool-1.0.3.data/data/etc/oos/playbooks/kolla.yaml
openstack_sig_tool-1.0.3.data/data/etc/oos/playbooks/mariadb.yaml
openstack_sig_tool-1.0.3.data/data/etc/oos/playbooks/memcached.yaml
openstack_sig_tool-1.0.3.data/data/etc/oos/playbooks/neutron.yaml
openstack_sig_tool-1.0.3.dist-info/AUTHORS
openstack_sig_tool-1.0.3.dist-info/LICENSE
openstack_sig_tool-1.0.3.dist-info/METADATA
openstack_sig_tool-1.0.3.dist-info/WHEEL
openstack_sig_tool-1.0.3.dist-info/entry_points.txt
openstack_sig_tool-1.0.3.dist-info/pbr.json
openstack_sig_tool-1.0.3.dist-info/top_level.txt
openstack_sig_tool-1.0.3.dist-info/RECORD
