Metadata-Version: 2.1
Name: openstack-sig-tool
Version: 1.0.3
Summary: The command line tool for openEuler OpenStack SIG
Home-page: https://gitee.com/openeuler/openstack/
Author: openEuler OpenStack SIG
License: UNKNOWN
Platform: UNKNOWN
Classifier: Intended Audience :: Information Technology
Classifier: Intended Audience :: System Administrators
Classifier: License :: OSI Approved :: Apache Software License
Classifier: Operating System :: POSIX :: Linux
Classifier: Programming Language :: Python
Classifier: Programming Language :: Python :: 3
Classifier: Programming Language :: Python :: 3.7
Classifier: Programming Language :: Python :: 3.8
Classifier: Programming Language :: Python :: 3.9
Requires-Python: >=3.7
Requires-Dist: Jinja2
Requires-Dist: ansible (==2.9.27)
Requires-Dist: bs4
Requires-Dist: click
Requires-Dist: lxml
Requires-Dist: markdown
Requires-Dist: packaging
Requires-Dist: pandas
Requires-Dist: pymdown-extensions
Requires-Dist: pyyaml
Requires-Dist: requests
Requires-Dist: xmltodict
